src/__init__.py
src/bin/ffmpeg
src/cut_video.py
src/ffmpeg.py
src/server.py
ffmpeg_mcp-0.1.2.dist-info/METADATA
ffmpeg_mcp-0.1.2.dist-info/WHEEL
ffmpeg_mcp-0.1.2.dist-info/RECORD
